sproing/__init__.py
sproing/container.py
sproing/dependency.py
sproing/injection.py
sproing-0.1.0.dist-info/METADATA
sproing-0.1.0.dist-info/WHEEL
sproing-0.1.0.dist-info/RECORD
